cartography_openapi/__init__.py
cartography_openapi/__main__.py
cartography_openapi/_version.py
cartography_openapi/checklist.py
cartography_openapi/component.py
cartography_openapi/entity.py
cartography_openapi/module.py
cartography_openapi/pagination.py
cartography_openapi/parser.py
cartography_openapi/path.py
cartography_openapi/templates/docs_config.jinja
cartography_openapi/templates/docs_index.jinja
cartography_openapi/templates/docs_schema.jinja
cartography_openapi/templates/intel.jinja
cartography_openapi/templates/intel_entity.jinja
cartography_openapi/templates/intel_sync_call.jinja
cartography_openapi/templates/model.jinja
cartography_openapi/templates/pr.jinja
cartography_openapi/templates/tests_data.jinja
cartography_openapi/templates/tests_integration.jinja
cartography_openapi-0.5.1.dist-info/licenses/LICENSE
cartography_openapi-0.5.1.dist-info/METADATA
cartography_openapi-0.5.1.dist-info/WHEEL
cartography_openapi-0.5.1.dist-info/top_level.txt
cartography_openapi-0.5.1.dist-info/RECORD
