Metadata-Version: 2.4
Name: cartography-openapi
Version: 0.5.1
Summary: A intel plugin builder for cartography for API supporting OpenAPI.
Author-email: Jeremy Chapeau <jeremy.chapeau@gmail.com>
License-Expression: Apache-2.0
Project-URL: Homepage, https://github.com/jychp/cartography-openapi
Project-URL: Download, https://github.com/jychp/cartography-openapi/releases
Project-URL: Bug Report, https://github.com/jychp/cartography-openapi/issues
Requires-Python: >=3.10
License-File: LICENSE
Requires-Dist: loguru>=0.7.3
Requires-Dist: jinja2>=3.1.6
Requires-Dist: requests>=2.32.3
Dynamic: license-file
